dynamic_process_pool/.git/COMMIT_EDITMSG
dynamic_process_pool/.git/FETCH_HEAD
dynamic_process_pool/.git/HEAD
dynamic_process_pool/.git/ORIG_HEAD
dynamic_process_pool/.git/config
dynamic_process_pool/.git/description
dynamic_process_pool/.git/hooks/applypatch-msg.sample
dynamic_process_pool/.git/hooks/commit-msg.sample
dynamic_process_pool/.git/hooks/fsmonitor-watchman.sample
dynamic_process_pool/.git/hooks/post-update.sample
dynamic_process_pool/.git/hooks/pre-applypatch.sample
dynamic_process_pool/.git/hooks/pre-commit.sample
dynamic_process_pool/.git/hooks/pre-merge-commit.sample
dynamic_process_pool/.git/hooks/pre-push.sample
dynamic_process_pool/.git/hooks/pre-rebase.sample
dynamic_process_pool/.git/hooks/pre-receive.sample
dynamic_process_pool/.git/hooks/prepare-commit-msg.sample
dynamic_process_pool/.git/hooks/push-to-checkout.sample
dynamic_process_pool/.git/hooks/update.sample
dynamic_process_pool/.git/index
dynamic_process_pool/.git/info/exclude
dynamic_process_pool/.git/logs/HEAD
dynamic_process_pool/.git/logs/refs/heads/main
dynamic_process_pool/.git/logs/refs/remotes/origin/main
dynamic_process_pool/.git/objects/00/00701cda4422c877b172e4da7e3fc33166ef96
dynamic_process_pool/.git/objects/02/c8a716f0c6a3fbdf4d030ac763b3905e59b476
dynamic_process_pool/.git/objects/0b/9c6c758b6dde934d9b9f5102735e880485d644
dynamic_process_pool/.git/objects/0e/7c254ba9211de9ff4a9b5a46079c9cf6159fb2
dynamic_process_pool/.git/objects/0e/b63a3329c2b77060ea6769fd622214082dd518
dynamic_process_pool/.git/objects/0e/b77e177aa487b1d38f6283220c7414dc26f696
dynamic_process_pool/.git/objects/0e/bb197673bd856b4f191b3b0121ba291729fc0a
dynamic_process_pool/.git/objects/10/63963fbdbe7bbe735f9ba9197c08b64a0672bd
dynamic_process_pool/.git/objects/12/7c9cd7d88aaf71e7dc70fee7d58e2106a6e887
dynamic_process_pool/.git/objects/16/325f92de2c2fc64ad64b2aef23c78fc5e9059e
dynamic_process_pool/.git/objects/16/e22c85f5009404a7caab1d38616944e985d4d4
dynamic_process_pool-0.2.0.dist-info/METADATA
dynamic_process_pool-0.2.0.dist-info/WHEEL
dynamic_process_pool-0.2.0.dist-info/RECORD
