Metadata-Version: 2.1
Name: dynamic-process-pool
Version: 0.2.0
Summary: 
Author: Pulkith Paruchuri
Author-email: pulkith.pa@gmail.com
Requires-Python: >=3.11,<4.0
Classifier: Programming Language :: Python :: 3
Classifier: Programming Language :: Python :: 3.11
Classifier: Programming Language :: Python :: 3.12
Requires-Dist: asyncio (>=3.4.3,<4.0.0)
Requires-Dist: uuid (>=1.30,<2.0)
